mufi/__init__.py
mufi/mufi.py
mufi/mufi_recs.py
mufi-0.2.0.dist-info/LICENSE
mufi-0.2.0.dist-info/METADATA
mufi-0.2.0.dist-info/WHEEL
mufi-0.2.0.dist-info/entry_points.txt
mufi-0.2.0.dist-info/top_level.txt
mufi-0.2.0.dist-info/RECORD
