Metadata-Version: 2.1
Name: mufi
Version: 0.2.0
Summary: Mufi: simple music finder for command-line
Home-page: http://github.com/maximtrp/mufi
Author: Maksim Terpilowski
Author-email: maximtrp@gmail.com
License: BSD
Keywords: python music cli
Platform: UNKNOWN
Classifier: Development Status :: 3 - Alpha
Classifier: Intended Audience :: Information Technology
Classifier: Intended Audience :: End Users/Desktop
Classifier: Topic :: Home Automation
Classifier: Topic :: Internet
Classifier: Topic :: Text Processing :: General
Classifier: License :: OSI Approved :: BSD License
Classifier: Programming Language :: Python :: 3
Classifier: Programming Language :: Python :: 3.5
Classifier: Programming Language :: Python :: 3.6
Classifier: Programming Language :: Python :: 3.7
Requires-Dist: selenium
